motivation/__init__.py
motivation/commands.py
motivation/test_commands.py
motivation-3.0.dist-info/LICENSE.txt
motivation-3.0.dist-info/METADATA
motivation-3.0.dist-info/RECORD
motivation-3.0.dist-info/WHEEL
motivation-3.0.dist-info/entry_points.txt
motivation-3.0.dist-info/namespace_packages.txt
motivation-3.0.dist-info/top_level.txt
