Metadata-Version: 2.1
Name: motivation
Version: 3.0
Summary: motivation
Home-page: https://github.com/yougov/motivation
Author: YouGov, Plc.
Author-email: open-source@yougov.com
License: UNKNOWN
Platform: UNKNOWN
Classifier: Development Status :: 5 - Production/Stable
Classifier: Intended Audience :: Developers
Classifier: License :: OSI Approved :: MIT License
Classifier: Programming Language :: Python :: 3
Requires-Python: >=3.6
Provides-Extra: docs
Provides-Extra: testing
Requires-Dist: ftfy
Provides-Extra: docs
Requires-Dist: sphinx; extra == 'docs'
Requires-Dist: jaraco.packaging (>=3.2); extra == 'docs'
Requires-Dist: rst.linker (>=1.9); extra == 'docs'
Provides-Extra: testing
Requires-Dist: pytest (>=3.5); extra == 'testing'
Requires-Dist: pytest-sugar (>=0.9.1); extra == 'testing'
Requires-Dist: collective.checkdocs; extra == 'testing'
Requires-Dist: pytest-flake8; extra == 'testing'
Requires-Dist: pmxbot; extra == 'testing'
Requires-Dist: responses; extra == 'testing'
